odoo/addons/stock_move_change_source_location/README.rst
odoo/addons/stock_move_change_source_location/__init__.py
odoo/addons/stock_move_change_source_location/__manifest__.py
odoo/addons/stock_move_change_source_location/i18n/de.po
odoo/addons/stock_move_change_source_location/i18n/it.po
odoo/addons/stock_move_change_source_location/i18n/stock_move_change_source_location.pot
odoo/addons/stock_move_change_source_location/readme/CONTRIBUTORS.rst
odoo/addons/stock_move_change_source_location/readme/DESCRIPTION.rst
odoo/addons/stock_move_change_source_location/readme/USAGE.rst
odoo/addons/stock_move_change_source_location/security/ir.model.access.csv
odoo/addons/stock_move_change_source_location/static/description/icon.png
odoo/addons/stock_move_change_source_location/static/description/index.html
odoo/addons/stock_move_change_source_location/tests/__init__.py
odoo/addons/stock_move_change_source_location/tests/test_stock_move_change_source_location.py
odoo/addons/stock_move_change_source_location/views/stock_picking_view.xml
odoo/addons/stock_move_change_source_location/wizards/__init__.py
odoo/addons/stock_move_change_source_location/wizards/stock_move_change_source_location_wizard.py
odoo/addons/stock_move_change_source_location/wizards/stock_move_change_source_location_wizard.xml
odoo_addon_stock_move_change_source_location-15.0.1.0.0.7.dist-info/METADATA
odoo_addon_stock_move_change_source_location-15.0.1.0.0.7.dist-info/WHEEL
odoo_addon_stock_move_change_source_location-15.0.1.0.0.7.dist-info/top_level.txt
odoo_addon_stock_move_change_source_location-15.0.1.0.0.7.dist-info/RECORD
